LICENSE
snakypy/helpers/__init__.py
snakypy/helpers/__main__.py
snakypy/helpers/ansi/__init__.py
snakypy/helpers/calcs/__init__.py
snakypy/helpers/calcs/bmi.py
snakypy/helpers/calcs/math.py
snakypy/helpers/catches/__init__.py
snakypy/helpers/catches/finders.py
snakypy/helpers/catches/generic.py
snakypy/helpers/checking/__init__.py
snakypy/helpers/checking/generic.py
snakypy/helpers/console/__init__.py
snakypy/helpers/console/display.py
snakypy/helpers/console/utils.py
snakypy/helpers/decorators/__init__.py
snakypy/helpers/files/__init__.py
snakypy/helpers/files/generic.py
snakypy/helpers/files/json.py
snakypy/helpers/logging/__init__.py
snakypy/helpers/os/__init__.py
snakypy/helpers/os/modifiers.py
snakypy/helpers/os/removals.py
snakypy/helpers/path/__init__.py
snakypy/helpers/subprocess/__init__.py
snakypy_helpers-0.3.1.dist-info/LICENSE
snakypy_helpers-0.3.1.dist-info/WHEEL
snakypy_helpers-0.3.1.dist-info/METADATA
snakypy_helpers-0.3.1.dist-info/RECORD
