Metadata-Version: 2.1
Name: snakypy-helpers
Version: 0.3.1
Summary: Snakypy Helpers is a package that contains code ready to assist in the development of packages/applications so as not to replicate the code.
Home-page: https://github.com/snakypy/snakypy-helpers
License: MIT
Keywords: snakypy,helpers,linux
Author: William C. Canin
Author-email: william.costa.canin@gmail.com
Requires-Python: >=3.9,<4.0
Classifier: License :: OSI Approved :: MIT License
Classifier: Programming Language :: Python :: 3
Classifier: Programming Language :: Python :: 3.10
Classifier: Programming Language :: Python :: 3.9
Requires-Dist: pyfiglet (==0.8.post1)
Project-URL: Repository, https://github.com/snakypy/snakypy-helpers
